same_version/__init__.py
same_version/log_collector.py
same_version/main.py
same_version/checkers/__init__.py
same_version/checkers/cargo_toml_checker.py
same_version/checkers/checker.py
same_version/checkers/citation_cff_checker.py
same_version/checkers/codemeta_json_checker.py
same_version/checkers/composer_json_checker.py
same_version/checkers/file_checker.py
same_version/checkers/github_event_checker.py
same_version/checkers/nuspec_checker.py
same_version/checkers/package_json_checker.py
same_version/checkers/pom_xml_checker.py
same_version/checkers/py_version_assignment_checker.py
same_version/checkers/pyproject_toml_checker.py
same_version/checkers/r_description_checker.py
same_version/checkers/ro_crate_metadata_json_checker.py
same_version/checkers/setup_cfg_checker.py
same_version/checkers/setup_py_checker.py
same_version/checkers/zenodo_json_checker.py
same_version/extractors/__init__.py
same_version/extractors/cargo_toml_extractor.py
same_version/extractors/citation_cff_extractor.py
same_version/extractors/cli_extractor.py
same_version/extractors/codemeta_json_extractor.py
same_version/extractors/composer_json_extractor.py
same_version/extractors/extractor.py
same_version/extractors/file_extractor.py
same_version/extractors/github_event_extractor.py
same_version/extractors/ini_extractor.py
same_version/extractors/json_extractor.py
same_version/extractors/nuspec_extractor.py
same_version/extractors/package_json_extractor.py
same_version/extractors/pom_xml_extractor.py
same_version/extractors/py_ast_extractor.py
same_version/extractors/py_version_assignment_extractor.py
same_version/extractors/pyproject_toml_extractor.py
same_version/extractors/r_description_extractor.py
same_version/extractors/ro_crate_metadata_json_extractor.py
same_version/extractors/setup_cfg_extractor.py
same_version/extractors/setup_py_extractor.py
same_version/extractors/toml_extractor.py
same_version/extractors/xml_extractor.py
same_version/extractors/yaml_extractor.py
same_version-7.1.0.dist-info/METADATA
same_version-7.1.0.dist-info/WHEEL
same_version-7.1.0.dist-info/entry_points.txt
same_version-7.1.0.dist-info/licenses/LICENSE
same_version-7.1.0.dist-info/RECORD
