Metadata-Version: 2.4
Name: same-version
Version: 7.1.0
Summary: Automatically ensures your software version metadata is consistent across key project files.
Project-URL: Homepage, https://github.com/willynilly/same-version
Project-URL: Documentation, https://github.com/willynilly/same-version#readme
Project-URL: Issues, https://github.com/willynilly/same-version/issues
Project-URL: Source, https://github.com/willynilly/same-version
Author-email: Will Riley <wanderingwill@gmail.com>
License-Expression: Apache-2.0
License-File: LICENSE
Keywords: .zenodo.json,CFF,CI/CD,CITATION.cff,CodeMeta,DevOps,FAIR,GitHub Action,Zenodo,citation,codemeta.json,harmonization,metadata,open science,package.json,pyproject.toml,setup.py,software quality,version
Classifier: Development Status :: 3 - Alpha
Classifier: Intended Audience :: Developers
Classifier: Intended Audience :: Science/Research
Classifier: License :: OSI Approved :: Apache Software License
Classifier: Natural Language :: English
Classifier: Operating System :: OS Independent
Classifier: Programming Language :: Python :: 3.10
Classifier: Programming Language :: Python :: 3.11
Classifier: Programming Language :: Python :: 3.12
Classifier: Programming Language :: Python :: 3.13
Classifier: Topic :: Scientific/Engineering
Classifier: Topic :: Software Development
Classifier: Topic :: Software Development :: Libraries :: Python Modules
Classifier: Topic :: Software Development :: Version Control
Classifier: Topic :: Utilities
Requires-Python: >=3.10
Requires-Dist: pyyaml>=6.0.2
Requires-Dist: tomli>=2.2.1
Requires-Dist: verple>=1.0.0
Provides-Extra: dev
Requires-Dist: pre-commit>=4.2.0; extra == 'dev'
Requires-Dist: ruff>=0.11.12; extra == 'dev'
Provides-Extra: testing
Requires-Dist: pytest>=8.3.5; extra == 'testing'
